.travis.yml
README.rst
base.cfg
bootstrap.py
buildout.cfg
development.cfg
pre-commit-check.sh
setup.cfg
setup.py
travis.cfg
versions.cfg
docs/HISTORY.rst
docs/LICENSE.rst
docs/conf.py
docs/conventions.rst
docs/dev.rst
docs/index.rst
docs/release.rst
docs/source.rst
src/niteoweb/__init__.py
src/niteoweb.click2sell.egg-info/PKG-INFO
src/niteoweb.click2sell.egg-info/SOURCES.txt
src/niteoweb.click2sell.egg-info/dependency_links.txt
src/niteoweb.click2sell.egg-info/entry_points.txt
src/niteoweb.click2sell.egg-info/namespace_packages.txt
src/niteoweb.click2sell.egg-info/not-zip-safe
src/niteoweb.click2sell.egg-info/requires.txt
src/niteoweb.click2sell.egg-info/top_level.txt
src/niteoweb/click2sell/__init__.py
src/niteoweb/click2sell/config.py
src/niteoweb/click2sell/configure.zcml
src/niteoweb/click2sell/interfaces.py
src/niteoweb/click2sell/version.txt
src/niteoweb/click2sell/browser/__init__.py
src/niteoweb/click2sell/browser/click2sell.py
src/niteoweb/click2sell/browser/click2sell_icon.png
src/niteoweb/click2sell/browser/configure.zcml
src/niteoweb/click2sell/browser/controlpanel.py
src/niteoweb/click2sell/browser/email.pt
src/niteoweb/click2sell/profiles/default/controlpanel.xml
src/niteoweb/click2sell/profiles/default/memberdata_properties.xml
src/niteoweb/click2sell/profiles/default/metadata.xml
src/niteoweb/click2sell/profiles/default/propertiestool.xml
src/niteoweb/click2sell/profiles/default/registry.xml
src/niteoweb/click2sell/profiles/default/rolemap.xml
src/niteoweb/click2sell/tests/__init__.py
src/niteoweb/click2sell/tests/base.py
src/niteoweb/click2sell/tests/control_panel.txt
src/niteoweb/click2sell/tests/test_click2sell.py
src/niteoweb/click2sell/tests/test_doctest.py
src/niteoweb/click2sell/tests/test_setup.py
src/niteoweb/click2sell/upgrades/__init__.py
src/niteoweb/click2sell/upgrades/configure.zcml
src/niteoweb/click2sell/upgrades/upgrade_0_to_0400.py