Metadata-Version: 1.0
Name: niteoweb.click2sell
Version: 0.4.5
Summary: Integrates click2sell digital products retailer system with Plone for paid memberships.
Home-page: http://www.niteoweb.com
Author: NiteoWeb Ltd.
Author-email: info@niteoweb.com
License: BSD
Keywords: Plone Python click2sell
Platform: UNKNOWN
Classifier: Framework :: Plone
Classifier: Programming Language :: Python
